[["achievements",{"version":2,"data":{"vecHighlight":[],"vecUnachieved":[{"strID":"Bronze","strName":"Bronze","strDescription":"Reach Bronze Age in any city (granted when you unlock any technology in that age)","strImage":"https://cdn.steamstatic.com/steamcommunity/public/images/apps/2181940/835fb2df92fa2ac4191fb319c0fb7c097787c28a.jpg","bAchieved":false,"rtUnlocked":0,"flAchieved":40.70000076293945,"flMinProgress":0,"flCurrentProgress":0,"flMaxProgress":0},{"strID":"Iron","strName":"Iron","strDescription":"Reach Iron Age in any city (granted when you unlock any technology in that age)","strImage":"https://cdn.steamstatic.com/steamcommunity/public/images/apps/2181940/b1670308fa057bac93e42def183d1ce611604bb1.jpg","bAchieved":false,"rtUnlocked":0,"flAchieved":31.899999618530273,"flMinProgress":0,"flCurrentProgress":0,"flMaxProgress":0},{"strID":"Classical","strName":"Classical","strDescription":"Reach Classical Age in any city (granted when you unlock any technology in that age)","strImage":"https://cdn.steamstatic.com/steamcommunity/public/images/apps/2181940/4193782d01293e24e1217a186f8e206de2b9bbfa.jpg","bAchieved":false,"rtUnlocked":0,"flAchieved":23,"flMinProgress":0,"flCurrentProgress":0,"flMaxProgress":0},{"strID":"Medieval","strName":"Medieval","strDescription":"Reach Middle Age in any city (granted when you unlock any technology in that age)","strImage":"https://cdn.steamstatic.com/steamcommunity/public/images/apps/2181940/837e1d83daebb8e3c10ce56838fd47d23d463f8d.jpg","bAchieved":false,"rtUnlocked":0,"flAchieved":13.899999618530273,"flMinProgress":0,"flCurrentProgress":0,"flMaxProgress":0},{"strID":"PaxRomana","strName":"Pax Romana","strDescription":"Rebirth with at least 1 Extra Great Person when playing Roman (Reach 64M Empire Value when rebirth)","strImage":"https://cdn.steamstatic.com/steamcommunity/public/images/apps/2181940/8fcb7dd0ae190f0c7e577c3201683417016cc6ff.jpg","bAchieved":false,"rtUnlocked":0,"flAchieved":12,"flMinProgress":0,"flCurrentProgress":0,"flMaxProgress":0},{"strID":"Renaissance","strName":"Renaissance","strDescription":"Reach Renaissance Age in any city (granted when you unlock any technology in that age)","strImage":"https://cdn.steamstatic.com/steamcommunity/public/images/apps/2181940/14cf74d491319ad90c4b4bd159c77be42a960e6c.jpg","bAchieved":false,"rtUnlocked":0,"flAchieved":10,"flMinProgress":0,"flCurrentProgress":0,"flMaxProgress":0},{"strID":"DemoPlayer","strName":"Founder","strDescription":"This achievement is awarded to players who played the game's demo. You can also earn this by reaching 100h play time on Steam","strImage":"https://cdn.steamstatic.com/steamcommunity/public/images/apps/2181940/1da4363cbc8ba8d1c8cfc660c9f549f5820d7fb6.jpg","bAchieved":false,"rtUnlocked":0,"flAchieved":6.699999809265137,"flMinProgress":0,"flCurrentProgress":0,"flMaxProgress":0},{"strID":"Industrial","strName":"Industrial","strDescription":"Reach Industrial Age in any city (granted when you unlock any technology in that age)","strImage":"https://cdn.steamstatic.com/steamcommunity/public/images/apps/2181940/a12e62482cb3744f479124ad423f169fba415ae9.jpg","bAchieved":false,"rtUnlocked":0,"flAchieved":6.300000190734863,"flMinProgress":0,"flCurrentProgress":0,"flMaxProgress":0},{"strID":"Olympian","strName":"Olympian","strDescription":"Rebirth with at least 1 Extra Great Person when playing Greek (Reach 64M Empire Value when rebirth)","strImage":"https://cdn.steamstatic.com/steamcommunity/public/images/apps/2181940/b0aa430e2023184688f8619153c49189222fd1e4.jpg","bAchieved":false,"rtUnlocked":0,"flAchieved":5.099999904632568,"flMinProgress":0,"flCurrentProgress":0,"flMaxProgress":0},{"strID":"EyeOfHorus","strName":"Eye of Horus","strDescription":"Rebirth with at least 1 Extra Great Person when playing Egyptian (Reach 64M Empire Value when rebirth)","strImage":"https://cdn.steamstatic.com/steamcommunity/public/images/apps/2181940/2ad51e1dc303b6826a38252a5940cfe04975845c.jpg","bAchieved":false,"rtUnlocked":0,"flAchieved":4.400000095367432,"flMinProgress":0,"flCurrentProgress":0,"flMaxProgress":0},{"strID":"MandateOfHeaven","strName":"Mandate of Heaven","strDescription":"Rebirth with at least 1 Extra Great Person when playing Chinese (Reach 64M Empire Value when rebirth)","strImage":"https://cdn.steamstatic.com/steamcommunity/public/images/apps/2181940/081312f880f4b721f6da5909d0bc30a9406c4a07.jpg","bAchieved":false,"rtUnlocked":0,"flAchieved":3.5999999046325684,"flMinProgress":0,"flCurrentProgress":0,"flMaxProgress":0},{"strID":"WorldWars","strName":"World Wars","strDescription":"Reach World Wars Age in any city (granted when you unlock any technology in that age)","strImage":"https://cdn.steamstatic.com/steamcommunity/public/images/apps/2181940/4aa62b621d261eb38df8c4103168cfe8016b284b.jpg","bAchieved":false,"rtUnlocked":0,"flAchieved":3.4000000953674316,"flMinProgress":0,"flCurrentProgress":0,"flMaxProgress":0}],"vecAchievedHidden":[],"nTotal":19,"nAchieved":0}}]]