[["achievements",{"version":2,"data":{"vecHighlight":[],"vecUnachieved":[],"vecAchievedHidden":[],"nTotal":0,"nAchieved":0}}],["achievementmap",{"version":5,"data":"[]"}],["usernews",{"version":5,"data":[]}],["gameactivity",{"version":5,"data":[]}],["associations",{"version":2,"data":{"rgDevelopers":[{"strName":"ManaStorm Studios","strURL":null}],"rgPublishers":[{"strName":"ManaStorm Studios","strURL":null}],"rgFranchises":[]}}],["descriptions",{"version":1,"data":{"strFullDescription":"快加入 ScarQuest，您將有機會獲得極其珍貴的星球土地\r\n打造強大的進攻部隊，橫掃競技場，戰勝敵人獲得競技寶箱，\r\n就有機會獲得星球土地，成為星球主人之一，讓你的威名傳遍宇宙。\r\n\r\n● 經營與裝飾自己的星島\r\n可在島上興建多樣的建築，升級建築提高生產力，還能擴增進攻部隊的數量\r\n另外還有上百種的裝飾物，能將你的的基地打造出獨一無二的個人風格\r\n         \r\n● 強化你的基地，殲滅來敵\r\n十幾種防禦地形等待你的部屬，配合不同的陷阱、防禦塔以及強力的英雄，\r\n他們的位置都將隨你指揮，在你手中將能布置出千變萬化的防守陣容\r\n         \r\n● 在線防守，施放增援\r\n敵人來犯時，你可以即時進入防禦戰場觀戰\r\n依照戰況施放各種防守增援技能，阻饒敵人的進攻\r\n還可對敵人使用各種表情，分散敵人的注意力\r\n         \r\n● 訓練進攻部隊，掠奪資源\r\n數十位各具特色的英雄，可搭配出多種不同的進攻戰術與組合\r\n你可以和敵人正面硬剛，也可以運用傳送能力，直接偷襲對方的主堡\r\n掠奪手下敗將的資源，進一步壯大自己的部隊\r\n         \r\n● 消滅異種，獲得豐厚賞金\r\n遭遇入侵宇宙的異種艦隊，消滅他們賺取豐厚賞金\r\n但是敵人的實力也不容小覷，不可冒進，安全第一\r\n\r\n之後還會加入更多新奇有趣的玩法，\r\n還等甚麼!! 趕快加入 ScarQuest 稱霸宇宙吧!!","strSnippet":"打造強大的部隊橫掃星海，將有機會獲得珍貴的星球土地，成為星球的主人"}}]]