[["achievements",{"version":2,"data":{"vecHighlight":[],"vecUnachieved":[],"vecAchievedHidden":[],"nTotal":0,"nAchieved":0}}],["achievementmap",{"version":5,"data":"[]"}],["usernews",{"version":5,"data":[]}],["gameactivity",{"version":5,"data":[]}],["socialmedia",{"version":3,"data":[]}],["associations",{"version":2,"data":{"rgDevelopers":[{"strName":"TinyMindz","strURL":null}],"rgPublishers":[{"strName":"TinyMindz","strURL":null}],"rgFranchises":[]}}],["descriptions",{"version":1,"data":{"strFullDescription":"[h2]Welcome to Cakey's Twisted Bakery![/h2]\r\n\r\nIt's bake or die at Cakey's Bakery, where human children are the secret ingredient to strange monsters' delicious pastries. Find the recipe for survival to escape the bakery and it's sweet and scary staff! You're searching for your little brother, George, who has gone missing somewhere in the bakery. To rescue him, you must face the challenges of Cakey and his crumbly companions: Frostina and Candy Bane.\r\n\r\nGather ingredients to bake the perfect pie of destruction to use against the roaming bakery baddies. But be careful! This won't be a walk in the park. One wrong step and you'll find yourself as the next course in a monster meal. Hide and sneak your way through many dark rooms to unlock your way home.\r\n\r\nIt's time to bake or die at Cakey's Twisted Bakery!","strSnippet":"It's bake or die at Cakey's Bakery, where human children are the secret ingredient to strange monsters' delicious pastries. Find the recipe for survival to escape the bakery and it's sweet and scary staff!"}}]]