[["achievements",{"version":2,"data":{"vecHighlight":[],"vecUnachieved":[{"strID":"KEY_001","strName":"Factory Tour","strDescription":"Unlock Processing","strImage":"https://cdn.steamstatic.com/steamcommunity/public/images/apps/3028500/8efa5f158b8c65cd88fcb3231cfde4006f000929.jpg","bAchieved":false,"rtUnlocked":0,"flAchieved":10.600000381469727,"flMinProgress":0,"flCurrentProgress":0,"flMaxProgress":0},{"strID":"COLLECT_BASKET","strName":"Sugar Rush","strDescription":"Acquire the Basket","strImage":"https://cdn.steamstatic.com/steamcommunity/public/images/apps/3028500/8efa5f158b8c65cd88fcb3231cfde4006f000929.jpg","bAchieved":false,"rtUnlocked":0,"flAchieved":9.5,"flMinProgress":0,"flCurrentProgress":0,"flMaxProgress":0},{"strID":"KEY_002","strName":"Hot and Cold","strDescription":"Unlock Shipping","strImage":"https://cdn.steamstatic.com/steamcommunity/public/images/apps/3028500/8efa5f158b8c65cd88fcb3231cfde4006f000929.jpg","bAchieved":false,"rtUnlocked":0,"flAchieved":9.199999809265137,"flMinProgress":0,"flCurrentProgress":0,"flMaxProgress":0},{"strID":"KEY_003","strName":"Go To The Light","strDescription":"Unlock the Exit","strImage":"https://cdn.steamstatic.com/steamcommunity/public/images/apps/3028500/8efa5f158b8c65cd88fcb3231cfde4006f000929.jpg","bAchieved":false,"rtUnlocked":0,"flAchieved":8.699999809265137,"flMinProgress":0,"flCurrentProgress":0,"flMaxProgress":0},{"strID":"COLLECT_BACKPACK","strName":"Super Stylish!","strDescription":"Acquire the Backpack","strImage":"https://cdn.steamstatic.com/steamcommunity/public/images/apps/3028500/8efa5f158b8c65cd88fcb3231cfde4006f000929.jpg","bAchieved":false,"rtUnlocked":0,"flAchieved":8.100000381469727,"flMinProgress":0,"flCurrentProgress":0,"flMaxProgress":0},{"strID":"BAD_ENDING","strName":"Explain That To Mom","strDescription":"Leave George Behind","strImage":"https://cdn.steamstatic.com/steamcommunity/public/images/apps/3028500/8efa5f158b8c65cd88fcb3231cfde4006f000929.jpg","bAchieved":false,"rtUnlocked":0,"flAchieved":7.900000095367432,"flMinProgress":0,"flCurrentProgress":0,"flMaxProgress":0},{"strID":"INGREDIENT_002","strName":"Grave Robber","strDescription":"Collect 100 Flesh Cubes","strImage":"https://cdn.steamstatic.com/steamcommunity/public/images/apps/3028500/8efa5f158b8c65cd88fcb3231cfde4006f000929.jpg","bAchieved":false,"rtUnlocked":0,"flAchieved":5.900000095367432,"flMinProgress":0,"flCurrentProgress":0,"flMaxProgress":100},{"strID":"GOOD_ENDING","strName":"Good Sister","strDescription":"Save George","strImage":"https://cdn.steamstatic.com/steamcommunity/public/images/apps/3028500/8efa5f158b8c65cd88fcb3231cfde4006f000929.jpg","bAchieved":false,"rtUnlocked":0,"flAchieved":5.800000190734863,"flMinProgress":0,"flCurrentProgress":0,"flMaxProgress":0},{"strID":"INGREDIENT_001","strName":"Sweet Cubes","strDescription":"Collect 100 Aged Sugar","strImage":"https://cdn.steamstatic.com/steamcommunity/public/images/apps/3028500/8efa5f158b8c65cd88fcb3231cfde4006f000929.jpg","bAchieved":false,"rtUnlocked":0,"flAchieved":5.800000190734863,"flMinProgress":0,"flCurrentProgress":0,"flMaxProgress":100},{"strID":"INGREDIENT_003","strName":"Chocolate Hoarder","strDescription":"Collect 100 Canned Cocoa","strImage":"https://cdn.steamstatic.com/steamcommunity/public/images/apps/3028500/8efa5f158b8c65cd88fcb3231cfde4006f000929.jpg","bAchieved":false,"rtUnlocked":0,"flAchieved":5.800000190734863,"flMinProgress":0,"flCurrentProgress":0,"flMaxProgress":100},{"strID":"INGREDIENT_005","strName":"Dead Head","strDescription":"Collect 100 Brittle Bone","strImage":"https://cdn.steamstatic.com/steamcommunity/public/images/apps/3028500/8efa5f158b8c65cd88fcb3231cfde4006f000929.jpg","bAchieved":false,"rtUnlocked":0,"flAchieved":5.599999904632568,"flMinProgress":0,"flCurrentProgress":0,"flMaxProgress":100},{"strID":"INGREDIENT_004","strName":"Dairy World","strDescription":"Collect 100 Whole Milk","strImage":"https://cdn.steamstatic.com/steamcommunity/public/images/apps/3028500/8efa5f158b8c65cd88fcb3231cfde4006f000929.jpg","bAchieved":false,"rtUnlocked":0,"flAchieved":5.5,"flMinProgress":0,"flCurrentProgress":0,"flMaxProgress":100}],"vecAchievedHidden":[],"nTotal":21,"nAchieved":0}}],["achievementmap",{"version":5,"data":"[]"}],["usernews",{"version":5,"data":[]}],["gameactivity",{"version":5,"data":[]}],["socialmedia",{"version":3,"data":[]}],["associations",{"version":2,"data":{"rgDevelopers":[{"strName":"TinyMindz","strURL":null}],"rgPublishers":[{"strName":"TinyMindz","strURL":null}],"rgFranchises":[]}}],["descriptions",{"version":1,"data":{"strFullDescription":"[h2]Welcome to Cakey's Twisted Bakery![/h2]\r\n\r\nIt's bake or die at Cakey's Bakery, where human children are the secret ingredient to strange monsters' delicious pastries. Find the recipe for survival to escape the bakery and it's sweet and scary staff! You're searching for your little brother, George, who has gone missing somewhere in the bakery. To rescue him, you must face the challenges of Cakey and his crumbly companions: Frostina and Candy Bane.\r\n\r\nGather ingredients to bake the perfect pie of destruction to use against the roaming bakery baddies. But be careful! This won't be a walk in the park. One wrong step and you'll find yourself as the next course in a monster meal. Hide and sneak your way through many dark rooms to unlock your way home.\r\n\r\nIt's time to bake or die at Cakey's Twisted Bakery!","strSnippet":"It's bake or die at Cakey's Bakery, where human children are the secret ingredient to strange monsters' delicious pastries. Find the recipe for survival to escape the bakery and it's sweet and scary staff!"}}]]