[["achievements",{"version":2,"data":{"vecHighlight":[],"vecUnachieved":[],"vecAchievedHidden":[],"nTotal":0,"nAchieved":0}}],["socialmedia",{"version":3,"data":[]}],["associations",{"version":2,"data":{"rgDevelopers":[{"strName":"Storytaco","strURL":"https://store.steampowered.com/curator/45349688"}],"rgPublishers":[{"strName":"Storytaco","strURL":"https://store.steampowered.com/curator/45349688"}],"rgFranchises":[]}}],["descriptions",{"version":1,"data":{"strFullDescription":"[h2][b]關於Demo[/b][/h2][p]大家好！这里是 \\[ 阿西, 美女室友竟然...？] 的开发团队[/p][p]萬眾矚目的demo版終於上線啦！[/p][p]*以下功能和內容在demo版中被鎖定，感興趣的話可以在後續完整版中體驗~[/p][p][/p][list][*][p]在demo中，您[u]可以體驗到遊戲的 第一章[/u]，完整版共包括 6 個主要章節和 5 個結局。[/p][/*][/list][list][*][p]可以與其他用戶進行排名戰的喜愛度排行榜和投票系統暫時未解鎖。[/p][/*][*][p][u]第 1 章的章節進度獎勵暫時不可領取[/u][/p][/*][/list][p][/p][p]\r\n歡迎各位加入心愿單並多多轉發，讓好兄弟也來體驗試玩版，一起期待完整版吧！[/p][p][/p][h2][b]故事情節/出場人物[/b][/h2][p]\\[阿西, 美女室友竟然...？]是一款 FMV 真人視頻戀愛遊戲，你將以第一人稱與5位美女室友一起體驗別樣合租生活。[/p][p]在本作中，您將扮演合租公寓的房東男主 吳宥萬(直譯:牛奶男)，一直獨來獨往的你，生活中突然闖入 5 位性格各異美女租客[/p][p][/p][p]你們之間又將擦出怎樣的火花呢？[i]最後陪在你身邊的會是誰呢？[/i][/p][p][/p][p][b]第一位租客，相識20年的青梅竹馬：高末淑[/b][/p][p][img]https://shared.akamai.steamstatic.com/store_item_assets/steam/apps/3166530/extras/0827_고말숙2.gif?t=1731060588[/img][/p][p]&quot;你真的..只把我當朋友嗎？&quot;[/p][p][/p][p][b]第二位租客，初戀白月光, 過氣偶像：朴敏靜[/b][/p][p][img]https://shared.akamai.steamstatic.com/store_item_assets/steam/apps/3166530/extras/0827_박민정.gif?t=1731060588[/img][/p][p]&quot;我和哥哥的關係，不想只限於歌手和粉絲...&quot;[/p][p][/p][p][b]第三位租客，難搞的職場上司姐姐：佟圓圓[/b][/p][p][img]https://shared.akamai.steamstatic.com/store_item_assets/steam/apps/3166530/extras/0827_동그란.gif?t=1731060588[/img][/p][p]&quot;誒~ 真可愛，原來你喜歡這種play...？&quot;[/p][p][/p][p][b]第四位租客，天然呆的直球妹妹：高恩妃[/b][/p][p][img]https://shared.akamai.steamstatic.com/store_item_assets/steam/apps/3166530/extras/0827_고은비3.gif?t=1731060588[/img][/p][p]&quot;哥哥! 請和我結婚吧！&quot;[/p][p][/p][p][b]第五位租客，可愛的孤僻社恐宅女：曹聖依[/b][/p][p][img]https://shared.akamai.steamstatic.com/store_item_assets/steam/apps/3166530/extras/0827_조승이.gif?t=1731060588[/img][/p][p]&quot;你...你是來救我的嗎..?!&quot;[/p][p][/p][p]魅力各不相同的五個人，你最終會愛上誰呢?[/p][p]或者......也許你會愛上五個人之外的其他人..？[/p]","strSnippet":"“‘租客招募中！”一直獨自生活的吳宥萬，平淡的日常生活中突然闖入了5位美女租客。“青梅竹馬””、“初戀小偶像”、“霸道上司姐姐”、“天然呆的直球妹妹”和“孤僻社恐宅女”中，他應該選擇誰呢？"}}],["achievementmap",{"version":5,"data":"[]"}],["usernews",{"version":5,"data":[]}],["gameactivity",{"version":5,"data":[]}]]