[["achievementmap",{"version":5,"data":"[]"}],["usernews",{"version":5,"data":[]}],["gameactivity",{"version":5,"data":[]}],["achievements",{"version":2,"data":{"vecHighlight":[{"strID":"LEVEL_20","strName":"Evil Purge","strDescription":"Become Level 20","bAchieved":true,"rtUnlocked":1623419930,"strImage":"https://cdn.steamstatic.com/steamcommunity/public/images/apps/948510/df5d6bc40fcdba07286d0ffc6af8b75cc66a5329.jpg","bHidden":false,"flMinProgress":0,"flCurrentProgress":0,"flMaxProgress":0,"flAchieved":30},{"strID":"MONSTER_zomb","strName":"Back from the Dead","strDescription":"Unlock Zombies","bAchieved":true,"rtUnlocked":1622907934,"strImage":"https://cdn.steamstatic.com/steamcommunity/public/images/apps/948510/684b77cd90c952b51b231607d9548243ca6eff3c.jpg","bHidden":true,"flMinProgress":0,"flCurrentProgress":0,"flMaxProgress":0,"flAchieved":30.399999618530273},{"strID":"LEVEL_10","strName":"Monster Masher","strDescription":"Become Level 10","bAchieved":true,"rtUnlocked":1622905880,"strImage":"https://cdn.steamstatic.com/steamcommunity/public/images/apps/948510/12a5ae882c88d6085fe946c61c2773bbbe5aeec5.jpg","bHidden":false,"flMinProgress":0,"flCurrentProgress":0,"flMaxProgress":0,"flAchieved":50.20000076293945},{"strID":"MONSTER_mumm","strName":"Imhotep","strDescription":"Unlock Mummies","bAchieved":true,"rtUnlocked":1622905774,"strImage":"https://cdn.steamstatic.com/steamcommunity/public/images/apps/948510/74874af14f1c25de7a7f78e2dc3f7e996dab99e4.jpg","bHidden":true,"flMinProgress":0,"flCurrentProgress":0,"flMaxProgress":0,"flAchieved":51.29999923706055},{"strID":"LEVEL_3","strName":"Slayer","strDescription":"Become Level 3","bAchieved":true,"rtUnlocked":1622903094,"strImage":"https://cdn.steamstatic.com/steamcommunity/public/images/apps/948510/d162ddf57f84493438f1f86baa79f074d09af097.jpg","bHidden":false,"flMinProgress":0,"flCurrentProgress":0,"flMaxProgress":0,"flAchieved":63.29999923706055}],"vecUnachieved":[],"vecAchievedHidden":[{"strID":"MONSTER_mumm","strName":"Imhotep","strDescription":"Unlock Mummies","strImage":"https://cdn.steamstatic.com/steamcommunity/public/images/apps/948510/74874af14f1c25de7a7f78e2dc3f7e996dab99e4.jpg","bAchieved":true,"rtUnlocked":1622905774,"flAchieved":0},{"strID":"MONSTER_zomb","strName":"Back from the Dead","strDescription":"Unlock Zombies","strImage":"https://cdn.steamstatic.com/steamcommunity/public/images/apps/948510/684b77cd90c952b51b231607d9548243ca6eff3c.jpg","bAchieved":true,"rtUnlocked":1622907934,"flAchieved":0}],"nTotal":11,"nAchieved":5}}],["associations",{"version":2,"data":{"rgDevelopers":[{"strName":"Autotelic Games LLC","strURL":null}],"rgPublishers":[{"strName":"Autotelic Games LLC","strURL":null}],"rgFranchises":[]}}],["descriptions",{"version":1,"data":{"strFullDescription":"It's almost Halloween, and Monsters are attacking your City!  Can you defeat them all and save the Town?\r\n\r\nYou're going to have to build and collect a lot of monster parts, and use them to upgrade all of your skills to defeat the main boss!  Click and tap on all the special click modifiers for each monster to maximize your damage!\r\n\r\nYou'll also have to use Candy, which are special powers that let you do many different things in the game. Think very carefully on how to use them, because they don't come easy.\r\n\r\nYou'll also find rare resources which can level you up in mysterious ways in the future!\r\n\r\nFeatures\r\n-Leaderboard system\r\n-Full resolution monster animations\r\n-Compelling upgrade systems\r\n-Strategy mixed with idle and tap mechanics.\r\n\r\nDefeat evil in this Halloween themed Monster game!  Thanks for playing!","strSnippet":"Fight Halloween Monsters in this Idle Clicker! Upgrade your Skills! Defeat Evil!"}}]]